bb_cleanup/__init__.py
bb_cleanup/_cleanup.py
bb_cleanup/_find.py
bb_cleanup/cleanup.py
bb_cleanup/command.py
bb_cleanup/tests/__init__.py
bb_cleanup/tests/cleanup_test.py
bb_cleanup-0.1.32.dist-info/LICENSE
bb_cleanup-0.1.32.dist-info/METADATA
bb_cleanup-0.1.32.dist-info/WHEEL
bb_cleanup-0.1.32.dist-info/entry_points.txt
bb_cleanup-0.1.32.dist-info/top_level.txt
bb_cleanup-0.1.32.dist-info/RECORD
