Metadata-Version: 2.1
Name: bb_cleanup
Version: 0.1.32
Summary: clean files and directories using Unix-Shell Style wildcards
Home-page: https://github.com/taohoo/bb-cleanup
Author: HuBo
Author-email: taohoo@163.com
License: MIT License
Platform: all
Classifier: Programming Language :: Python :: 3
Classifier: Programming Language :: Python :: Implementation :: CPython
Classifier: Programming Language :: Python :: Implementation :: PyPy
Requires-Python: >=3.6
License-File: LICENSE
Requires-Dist: environs
